[
    {
        "lead_id": 1,
        "name": "John Doe",
        "phone": "+12345670001",
        "email": "johndoe1@example.com",
        "property_type": "sale",
        "budget": 300000,
        "location": "Los Angeles",
        "preferred_property_type": "house",
        "contact_date": "2024-01-05",
        "inquiry_notes": "Looking for a single-family house in a quiet neighborhood."
    },
    {
        "lead_id": 2,
        "name": "Jane Smith",
        "phone": "+12345670002",
        "email": "janesmith2@example.com",
        "property_type": "rental",
        "budget": 1500,
        "location": "San Francisco",
        "preferred_property_type": "apartment",
        "contact_date": "2024-01-06",
        "inquiry_notes": "Needs a pet-friendly apartment near public transportation."
    },
    {
        "lead_id": 3,
        "name": "John Doe",
        "phone": "+12345670001",
        "email": "johndoe1@example.com",
        "property_type": "rental",
        "budget": 1200,
        "location": "Los Angeles",
        "preferred_property_type": "apartment",
        "contact_date": "2024-02-01",
        "inquiry_notes": "Looking for a rental option as an interim solution."
    },
    {
        "lead_id": 4,
        "name": "Alice Johnson",
        "phone": "+12345670003",
        "email": "alicejohnson3@example.com",
        "property_type": "sale",
        "budget": 500000,
        "location": "New York",
        "preferred_property_type": "condo",
        "contact_date": "2024-01-07",
        "inquiry_notes": "Interested in a luxury condo with a view."
    },
    {
        "lead_id": 5,
        "name": "Charlie Davis",
        "phone": "+12345670004",
        "email": "charliedavis5@example.com",
        "property_type": "sale",
        "budget": 250000,
        "location": "Miami",
        "preferred_property_type": "townhouse",
        "contact_date": "2024-01-09",
        "inquiry_notes": "Searching for a family-friendly community."
    },
    {
        "lead_id": 6,
        "name": "Jane Smith",
        "phone": "+12345670002",
        "email": "janesmith2@example.com",
        "property_type": "sale",
        "budget": 280000,
        "location": "San Francisco",
        "preferred_property_type": "house",
        "contact_date": "2024-02-10",
        "inquiry_notes": "Considering purchasing after renting."
    },
    {
        "lead_id": 7,
        "name": "Bob Brown",
        "phone": "+12345670005",
        "email": "bobbrown7@example.com",
        "property_type": "rental",
        "budget": 1200,
        "location": "Chicago",
        "preferred_property_type": "apartment",
        "contact_date": "2024-01-08",
        "inquiry_notes": "Looking for a short-term rental."
    },
    {
        "lead_id": 8,
        "name": "Diane Garcia",
        "phone": "+12345670006",
        "email": "dianegarcia8@example.com",
        "property_type": "rental",
        "budget": 2200,
        "location": "Austin",
        "preferred_property_type": "house",
        "contact_date": "2024-01-10",
        "inquiry_notes": "Requires a backyard for children to play."
    },
    {
        "lead_id": 9,
        "name": "Alice Johnson",
        "phone": "+12345670003",
        "email": "alicejohnson3@example.com",
        "property_type": "rental",
        "budget": 2500,
        "location": "New York",
        "preferred_property_type": "apartment",
        "contact_date": "2024-02-15",
        "inquiry_notes": "Considering rental options in New York before deciding on a purchase."
    },
    {
        "lead_id": 10,
        "name": "George Wilson",
        "phone": "+12345670009",
        "email": "georgewilson10@example.com",
        "property_type": "sale",
        "budget": 600000,
        "location": "Seattle",
        "preferred_property_type": "apartment",
        "contact_date": "2024-01-13",
        "inquiry_notes": "Interested in high-rise apartment buildings."
    },
    {
        "lead_id": 11,
        "name": "Ivy Scott",
        "phone": "+12345670011",
        "email": "ivyscott11@example.com",
        "property_type": "rental",
        "budget": 1800,
        "location": "Los Angeles",
        "preferred_property_type": "condo",
        "contact_date": "2024-01-15",
        "inquiry_notes": "Looking for a modern condo with gym facilities."
    },
    {
        "lead_id": 12,
        "name": "Jack Taylor",
        "phone": "+12345670012",
        "email": "jacktaylor12@example.com",
        "property_type": "sale",
        "budget": 750000,
        "location": "San Diego",
        "preferred_property_type": "house",
        "contact_date": "2024-01-16",
        "inquiry_notes": "Seeking a large house with a backyard."
    },
    {
        "lead_id": 13,
        "name": "Laura White",
        "phone": "+12345670013",
        "email": "laurawhite13@example.com",
        "property_type": "rental",
        "budget": 1700,
        "location": "Chicago",
        "preferred_property_type": "apartment",
        "contact_date": "2024-01-17",
        "inquiry_notes": "Prefers a high-rise apartment with a view."
    },
    {
        "lead_id": 14,
        "name": "Mike Green",
        "phone": "+12345670014",
        "email": "mikegreen14@example.com",
        "property_type": "sale",
        "budget": 450000,
        "location": "Houston",
        "preferred_property_type": "townhouse",
        "contact_date": "2024-01-18",
        "inquiry_notes": "Looking for a townhouse in a gated community."
    },
    {
        "lead_id": 15,
        "name": "Nina Adams",
        "phone": "+12345670015",
        "email": "ninaadams15@example.com",
        "property_type": "rental",
        "budget": 1600,
        "location": "Austin",
        "preferred_property_type": "apartment",
        "contact_date": "2024-01-19",
        "inquiry_notes": "Wants an apartment close to downtown."
    },
    {
        "lead_id": 16,
        "name": "Oscar Bennett",
        "phone": "+12345670016",
        "email": "oscarbennett16@example.com",
        "property_type": "sale",
        "budget": 550000,
        "location": "Phoenix",
        "preferred_property_type": "house",
        "contact_date": "2024-01-20",
        "inquiry_notes": "Searching for a family house with a pool."
    },
    {
        "lead_id": 17,
        "name": "Pauline Harris",
        "phone": "+12345670017",
        "email": "paulineharris17@example.com",
        "property_type": "rental",
        "budget": 2000,
        "location": "Dallas",
        "preferred_property_type": "condo",
        "contact_date": "2024-01-21",
        "inquiry_notes": "Requires pet-friendly accommodation with parking."
    },
    {
        "lead_id": 18,
        "name": "Quinn Fisher",
        "phone": "+12345670018",
        "email": "quinnfisher18@example.com",
        "property_type": "sale",
        "budget": 320000,
        "location": "Orlando",
        "preferred_property_type": "townhouse",
        "contact_date": "2024-01-22",
        "inquiry_notes": "Prefers a quiet neighborhood with schools nearby."
    },
    {
        "lead_id": 19,
        "name": "Rachel King",
        "phone": "+12345670019",
        "email": "rachelking19@example.com",
        "property_type": "rental",
        "budget": 1300,
        "location": "Las Vegas",
        "preferred_property_type": "apartment",
        "contact_date": "2024-01-23",
        "inquiry_notes": "Looking for a budget-friendly apartment."
    },
    {
        "lead_id": 20,
        "name": "Sammy Young",
        "phone": "+12345670020",
        "email": "sammyyoung20@example.com",
        "property_type": "sale",
        "budget": 620000,
        "location": "Seattle",
        "preferred_property_type": "house",
        "contact_date": "2024-01-24",
        "inquiry_notes": "Interested in a property with lake views."
    },
    {
        "lead_id": 21,
        "name": "Timothy Brooks",
        "phone": "+12345670021",
        "email": "timothybrooks21@example.com",
        "property_type": "sale",
        "budget": 410000,
        "location": "Atlanta",
        "preferred_property_type": "house",
        "contact_date": "2024-01-25",
        "inquiry_notes": "Looking for a home near parks and green spaces."
    },
    {
        "lead_id": 22,
        "name": "Ursula Knight",
        "phone": "+12345670022",
        "email": "ursulaknight22@example.com",
        "property_type": "rental",
        "budget": 2000,
        "location": "Boston",
        "preferred_property_type": "apartment",
        "contact_date": "2024-01-26",
        "inquiry_notes": "Seeking an apartment with easy access to public transport."
    },
    {
        "lead_id": 23,
        "name": "Victor Perez",
        "phone": "+12345670023",
        "email": "victorperez23@example.com",
        "property_type": "sale",
        "budget": 700000,
        "location": "San Francisco",
        "preferred_property_type": "condo",
        "contact_date": "2024-01-27",
        "inquiry_notes": "Interested in a luxury condo with ocean views."
    },
    {
        "lead_id": 24,
        "name": "Wendy Thompson",
        "phone": "+12345670024",
        "email": "wendythompson24@example.com",
        "property_type": "rental",
        "budget": 1400,
        "location": "Miami",
        "preferred_property_type": "apartment",
        "contact_date": "2024-01-28",
        "inquiry_notes": "Needs a place with quick access to the beach."
    },
    {
        "lead_id": 25,
        "name": "Xavier Morgan",
        "phone": "+12345670025",
        "email": "xaviermorgan25@example.com",
        "property_type": "sale",
        "budget": 350000,
        "location": "Phoenix",
        "preferred_property_type": "townhouse",
        "contact_date": "2024-01-29",
        "inquiry_notes": "Looking for a townhouse with energy-efficient features."
    },
    {
        "lead_id": 26,
        "name": "Yara Reed",
        "phone": "+12345670026",
        "email": "yarareed26@example.com",
        "property_type": "rental",
        "budget": 1600,
        "location": "Denver",
        "preferred_property_type": "apartment",
        "contact_date": "2024-01-30",
        "inquiry_notes": "Prefers a quiet building with good security."
    },
    {
        "lead_id": 27,
        "name": "Zoe Campbell",
        "phone": "+12345670027",
        "email": "zoecampbell27@example.com",
        "property_type": "sale",
        "budget": 480000,
        "location": "Orlando",
        "preferred_property_type": "house",
        "contact_date": "2024-01-31",
        "inquiry_notes": "Needs a home in a family-friendly neighborhood."
    },
    {
        "lead_id": 28,
        "name": "Aaron Fisher",
        "phone": "+12345670028",
        "email": "aaronfisher28@example.com",
        "property_type": "rental",
        "budget": 2300,
        "location": "Los Angeles",
        "preferred_property_type": "condo",
        "contact_date": "2024-02-01",
        "inquiry_notes": "Looking for a place with access to a gym and pool."
    },
    {
        "lead_id": 29,
        "name": "Bella Simmons",
        "phone": "+12345670029",
        "email": "bellasimmons29@example.com",
        "property_type": "sale",
        "budget": 320000,
        "location": "Austin",
        "preferred_property_type": "townhouse",
        "contact_date": "2024-02-02",
        "inquiry_notes": "Interested in a townhouse with modern amenities."
    },
    {
        "lead_id": 30,
        "name": "Carlos Romero",
        "phone": "+12345670030",
        "email": "carlosromero30@example.com",
        "property_type": "rental",
        "budget": 1900,
        "location": "New York",
        "preferred_property_type": "apartment",
        "contact_date": "2024-02-03",
        "inquiry_notes": "Looking for an apartment close to work in Manhattan."
    },
    {
        "lead_id": 31,
        "name": "Dana Clarke",
        "phone": "+12345670031",
        "email": "danaclarke31@example.com",
        "property_type": "sale",
        "budget": 400000,
        "location": "Dallas",
        "preferred_property_type": "house",
        "contact_date": "2024-02-04",
        "inquiry_notes": "Looking for a suburban house with a large yard."
    },
    {
        "lead_id": 32,
        "name": "Evan Stewart",
        "phone": "+12345670032",
        "email": "evanstewart32@example.com",
        "property_type": "rental",
        "budget": 2200,
        "location": "San Diego",
        "preferred_property_type": "apartment",
        "contact_date": "2024-02-05",
        "inquiry_notes": "Interested in a downtown apartment close to amenities."
    },
    {
        "lead_id": 33,
        "name": "Fiona Hill",
        "phone": "+12345670033",
        "email": "fionahill33@example.com",
        "property_type": "sale",
        "budget": 275000,
        "location": "Nashville",
        "preferred_property_type": "condo",
        "contact_date": "2024-02-06",
        "inquiry_notes": "Looking for a modern condo in a vibrant area."
    },
    {
        "lead_id": 34,
        "name": "Gary Baker",
        "phone": "+12345670034",
        "email": "garybaker34@example.com",
        "property_type": "rental",
        "budget": 1500,
        "location": "Indianapolis",
        "preferred_property_type": "apartment",
        "contact_date": "2024-02-07",
        "inquiry_notes": "Needs a pet-friendly apartment with good parking."
    },
    {
        "lead_id": 35,
        "name": "Hannah Lee",
        "phone": "+12345670035",
        "email": "hannahlee35@example.com",
        "property_type": "sale",
        "budget": 550000,
        "location": "Seattle",
        "preferred_property_type": "house",
        "contact_date": "2024-02-08",
        "inquiry_notes": "Looking for a family-friendly neighborhood with parks nearby."
    },
    {
        "lead_id": 36,
        "name": "Isaac Wilson",
        "phone": "+12345670036",
        "email": "isaacwilson36@example.com",
        "property_type": "rental",
        "budget": 1800,
        "location": "Denver",
        "preferred_property_type": "condo",
        "contact_date": "2024-02-09",
        "inquiry_notes": "Looking for a high-rise condo with mountain views."
    },
    {
        "lead_id": 37,
        "name": "Julia Rogers",
        "phone": "+12345670037",
        "email": "juliarogers37@example.com",
        "property_type": "sale",
        "budget": 300000,
        "location": "Orlando",
        "preferred_property_type": "townhouse",
        "contact_date": "2024-02-10",
        "inquiry_notes": "Interested in a townhouse with energy-efficient features."
    },
    {
        "lead_id": 38,
        "name": "Kyle Martinez",
        "phone": "+12345670038",
        "email": "kylemartinez38@example.com",
        "property_type": "rental",
        "budget": 2500,
        "location": "San Jose",
        "preferred_property_type": "house",
        "contact_date": "2024-02-11",
        "inquiry_notes": "Looking for a rental home with a large kitchen and backyard."
    },
    {
        "lead_id": 39,
        "name": "Lily Evans",
        "phone": "+12345670039",
        "email": "lilyevans39@example.com",
        "property_type": "sale",
        "budget": 470000,
        "location": "Miami",
        "preferred_property_type": "condo",
        "contact_date": "2024-02-12",
        "inquiry_notes": "Prefers a beachfront condo with access to amenities."
    },
    {
        "lead_id": 40,
        "name": "Matt Thomas",
        "phone": "+12345670040",
        "email": "mattthomas40@example.com",
        "property_type": "rental",
        "budget": 1300,
        "location": "Philadelphia",
        "preferred_property_type": "apartment",
        "contact_date": "2024-02-13",
        "inquiry_notes": "Looking for an affordable rental near downtown."
    },
    {
        "lead_id": 41,
        "name": "Nina Hernandez",
        "phone": "+12345670041",
        "email": "ninahernandez41@example.com",
        "property_type": "sale",
        "budget": 600000,
        "location": "Charlotte",
        "preferred_property_type": "house",
        "contact_date": "2024-02-14",
        "inquiry_notes": "Looking for a luxury house with multiple bedrooms."
    },
    {
        "lead_id": 42,
        "name": "Oliver Bennett",
        "phone": "+12345670042",
        "email": "oliverbennett42@example.com",
        "property_type": "rental",
        "budget": 1400,
        "location": "Kansas City",
        "preferred_property_type": "apartment",
        "contact_date": "2024-02-15",
        "inquiry_notes": "Seeking a quiet apartment with easy highway access."
    },
    {
        "lead_id": 43,
        "name": "Paula Davis",
        "phone": "+12345670043",
        "email": "pauladavis43@example.com",
        "property_type": "sale",
        "budget": 290000,
        "location": "Baltimore",
        "preferred_property_type": "townhouse",
        "contact_date": "2024-02-16",
        "inquiry_notes": "Interested in a historic townhouse with character."
    },
    {
        "lead_id": 44,
        "name": "Quincy Carter",
        "phone": "+12345670044",
        "email": "quincycarter44@example.com",
        "property_type": "rental",
        "budget": 2100,
        "location": "Sacramento",
        "preferred_property_type": "house",
        "contact_date": "2024-02-17",
        "inquiry_notes": "Looking for a quiet rental with a spacious yard."
    },
    {
        "lead_id": 45,
        "name": "Rebecca Johnson",
        "phone": "+12345670045",
        "email": "rebeccajohnson45@example.com",
        "property_type": "sale",
        "budget": 320000,
        "location": "Salt Lake City",
        "preferred_property_type": "condo",
        "contact_date": "2024-02-18",
        "inquiry_notes": "Looking for a condo with mountain views."
    },
    {
        "lead_id": 46,
        "name": "Steve Young",
        "phone": "+12345670046",
        "email": "steveyoung46@example.com",
        "property_type": "rental",
        "budget": 1750,
        "location": "Portland",
        "preferred_property_type": "apartment",
        "contact_date": "2024-02-19",
        "inquiry_notes": "Seeking an eco-friendly building close to public transit."
    },
    {
        "lead_id": 47,
        "name": "Tina King",
        "phone": "+12345670047",
        "email": "tinaking47@example.com",
        "property_type": "sale",
        "budget": 530000,
        "location": "San Antonio",
        "preferred_property_type": "house",
        "contact_date": "2024-02-20",
        "inquiry_notes": "Looking for a modern home with smart features."
    },
    {
        "lead_id": 48,
        "name": "Ulysses Wright",
        "phone": "+12345670048",
        "email": "ulysseswright48@example.com",
        "property_type": "rental",
        "budget": 2300,
        "location": "Las Vegas",
        "preferred_property_type": "house",
        "contact_date": "2024-02-21",
        "inquiry_notes": "Seeking a house with a pool and a large yard."
    }
]